haxballgym/__init__.py
haxballgym/envs/__init__.py
haxballgym/envs/environment.py
haxballgym/envs/match.py
haxballgym/gym.py
haxballgym/make.py
haxballgym/utils/__init__.py
haxballgym/utils/action_parsers/__init__.py
haxballgym/utils/action_parsers/action_parser.py
haxballgym/utils/action_parsers/default_act.py
haxballgym/utils/action_parsers/discrete_act.py
haxballgym/utils/common_values.py
haxballgym/utils/gamestates/__init__.py
haxballgym/utils/gamestates/game_state.py
haxballgym/utils/obs_builders/__init__.py
haxballgym/utils/obs_builders/default_obs.py
haxballgym/utils/obs_builders/obs_builder.py
haxballgym/utils/reward_functions/__init__.py
haxballgym/utils/reward_functions/combined_reward.py
haxballgym/utils/reward_functions/common_rewards/__init__.py
haxballgym/utils/reward_functions/common_rewards/conditional_rewards.py
haxballgym/utils/reward_functions/common_rewards/misc_rewards.py
haxballgym/utils/reward_functions/default_reward.py
haxballgym/utils/reward_functions/reward_function.py
haxballgym/utils/reward_functions/velocity_reward.py
haxballgym/utils/state_setters/__init__.py
haxballgym/utils/state_setters/default_state.py
haxballgym/utils/state_setters/random_state.py
haxballgym/utils/state_setters/state_setter.py
haxballgym/utils/terminal_conditions/__init__.py
haxballgym/utils/terminal_conditions/common_conditions.py
haxballgym/utils/terminal_conditions/terminal_condition.py
haxballgym-0.5.8.dist-info/METADATA
haxballgym-0.5.8.dist-info/WHEEL
haxballgym-0.5.8.dist-info/RECORD
