Metadata-Version: 2.1
Name: haxballgym
Version: 0.5.8
Summary: HaxBallGym is a Python package that can be used to treat the game HaxBall as though it were an OpenAI-style environment for Reinforcement Learning projects.
Author: Wazarr
Author-email: jeje_04@live.com
Requires-Python: >=3.10,<3.11
Classifier: Programming Language :: Python :: 3
Classifier: Programming Language :: Python :: 3.10
Requires-Dist: gym (>=0.26.2,<0.27.0)
Requires-Dist: numpy (>=1.23.5,<2.0.0)
Requires-Dist: ursinaxball (>=0.2.4,<0.3.0)
